<?xml version="1.0" encoding="UTF-8"?><record_update table="sp_instance">
    <sp_instance action="DELETE">
        <active>true</active>
        <class_name/>
        <color>default</color>
        <css/>
        <glyph/>
        <id/>
        <order>4</order>
        <roles/>
        <short_description/>
        <size>md</size>
        <sp_column display_value="1">1dfcdf23c3341210a7705fd1b401317e</sp_column>
        <sp_widget display_value="SimpleLoginUI">9f3719eab32003007a6de81816a8dcd1</sp_widget>
        <sys_class_name>sp_instance</sys_class_name>
        <sys_created_by>admin</sys_created_by>
        <sys_created_on>2024-09-28 21:21:54</sys_created_on>
        <sys_id>f0d86723c3741210a7705fd1b4013194</sys_id>
        <sys_mod_count>0</sys_mod_count>
        <sys_name/>
        <sys_package display_value="Visitor Management" source="x_845458_visitorsa">3ab4f6ebc3301210a7705fd1b4013154</sys_package>
        <sys_policy/>
        <sys_scope display_value="Visitor Management">3ab4f6ebc3301210a7705fd1b4013154</sys_scope>
        <sys_update_name>sp_instance_f0d86723c3741210a7705fd1b4013194</sys_update_name>
        <sys_updated_by>admin</sys_updated_by>
        <sys_updated_on>2024-09-28 21:21:54</sys_updated_on>
        <title/>
        <url/>
        <widget_parameters/>
    </sp_instance>
    <sys_translated_text action="DELETE" query="documentkey=f0d86723c3741210a7705fd1b4013194"/>
    <sys_update_version action="INSERT_OR_UPDATE">
        <action>DELETE</action>
        <application display_value="Visitor Management">3ab4f6ebc3301210a7705fd1b4013154</application>
        <file_path/>
        <instance_id>32376ab41b0e7198699443f4bd4bcbfb</instance_id>
        <instance_name>dev191029</instance_name>
        <name>sp_instance_f0d86723c3741210a7705fd1b4013194</name>
        <payload><![CDATA[<?xml version="1.0" encoding="UTF-8"?><record_update table="sp_instance"><sp_instance action="INSERT_OR_UPDATE"><active>true</active><class_name/><color>default</color><css/><glyph/><id/><order>4</order><roles/><short_description/><size>md</size><sp_column display_value="1">1dfcdf23c3341210a7705fd1b401317e</sp_column><sp_widget display_value="SimpleLoginUI">9f3719eab32003007a6de81816a8dcd1</sp_widget><sys_class_name>sp_instance</sys_class_name><sys_created_by>admin</sys_created_by><sys_created_on>2024-09-28 21:21:54</sys_created_on><sys_id>f0d86723c3741210a7705fd1b4013194</sys_id><sys_mod_count>0</sys_mod_count><sys_name/><sys_package display_value="Visitor Management" source="x_845458_visitorsa">3ab4f6ebc3301210a7705fd1b4013154</sys_package><sys_policy/><sys_scope display_value="Visitor Management">3ab4f6ebc3301210a7705fd1b4013154</sys_scope><sys_update_name>sp_instance_f0d86723c3741210a7705fd1b4013194</sys_update_name><sys_updated_by>admin</sys_updated_by><sys_updated_on>2024-09-28 21:21:54</sys_updated_on><title/><url/><widget_parameters/></sp_instance><sys_translated_text action="delete_multiple" query="documentkey=f0d86723c3741210a7705fd1b4013194"/></record_update>]]></payload>
        <payload_hash>1915326212</payload_hash>
        <record_name/>
        <reverted_from/>
        <source>03b4f6ebc3301210a7705fd1b4013159</source>
        <source_table>sys_update_set</source_table>
        <state>previous</state>
        <sys_created_by>admin</sys_created_by>
        <sys_created_on>2024-09-28 21:21:54</sys_created_on>
        <sys_id>b0d82f23c3741210a7705fd1b4013170</sys_id>
        <sys_mod_count>0</sys_mod_count>
        <sys_recorded_at>1923a82f7260000001</sys_recorded_at>
        <sys_updated_by>admin</sys_updated_by>
        <sys_updated_on>2024-09-28 21:21:54</sys_updated_on>
        <type>Instance</type>
        <update_guid>b4d82f23db7412109d2022ba58698c6f</update_guid>
        <update_guid_history>b4d82f23db7412109d2022ba58698c6f:1915326212</update_guid_history>
    </sys_update_version>
    <sys_metadata_delete action="INSERT_OR_UPDATE">
        <sys_audit_delete display_value="">0b7ca278c3011210a7705fd1b4013150</sys_audit_delete>
        <sys_class_name>sys_metadata_delete</sys_class_name>
        <sys_created_by>admin</sys_created_by>
        <sys_created_on>2024-10-02 14:10:40</sys_created_on>
        <sys_db_object display_value="" name="sp_instance">sp_instance</sys_db_object>
        <sys_id>4154463e83ae4b92b1e8b67b0a4b1f04</sys_id>
        <sys_metadata>f0d86723c3741210a7705fd1b4013194</sys_metadata>
        <sys_mod_count>0</sys_mod_count>
        <sys_name/>
        <sys_package display_value="Visitor Management" source="x_845458_visitorsa">3ab4f6ebc3301210a7705fd1b4013154</sys_package>
        <sys_parent/>
        <sys_policy/>
        <sys_scope display_value="Visitor Management">3ab4f6ebc3301210a7705fd1b4013154</sys_scope>
        <sys_scope_delete display_value="">e9e2c45299ed4c98a68cdb34d29bdd21</sys_scope_delete>
        <sys_update_name>sp_instance_f0d86723c3741210a7705fd1b4013194</sys_update_name>
        <sys_update_version display_value="sp_instance_f0d86723c3741210a7705fd1b4013194">b0d82f23c3741210a7705fd1b4013170</sys_update_version>
        <sys_updated_by>admin</sys_updated_by>
        <sys_updated_on>2024-10-02 14:10:40</sys_updated_on>
    </sys_metadata_delete>
</record_update>
